bindsnet/__init__.py
bindsnet/utils.py
bindsnet/analysis/__init__.py
bindsnet/analysis/plotting.py
bindsnet/analysis/visualization.py
bindsnet/conversion/__init__.py
bindsnet/datasets/__init__.py
bindsnet/datasets/preprocess.py
bindsnet/encoding/__init__.py
bindsnet/environment/__init__.py
bindsnet/evaluation/__init__.py
bindsnet/learning/__init__.py
bindsnet/learning/reward.py
bindsnet/models/__init__.py
bindsnet/network/__init__.py
bindsnet/network/monitors.py
bindsnet/network/nodes.py
bindsnet/network/topology.py
bindsnet/pipeline/__init__.py
bindsnet/pipeline/action.py
bindsnet/preprocessing/__init__.py
bindsnet-0.2.4.dist-info/LICENSE
bindsnet-0.2.4.dist-info/METADATA
bindsnet-0.2.4.dist-info/WHEEL
bindsnet-0.2.4.dist-info/top_level.txt
bindsnet-0.2.4.dist-info/RECORD
