Metadata-Version: 2.1
Name: bindsnet
Version: 0.2.4
Summary: Spiking neural networks for ML in Python
Home-page: http://github.com/Hananel-Hazan/bindsnet
Author: Daniel Saunders, Hananel Hazan, Darpan Sanghavi, Hassaan Khan
Author-email: danjsaund@gmail.com
License: AGPL-3.0
Download-URL: https://github.com/Hananel-Hazan/bindsnet/archive/0.2.4.tar.gz
Platform: UNKNOWN
Requires-Dist: numpy (>=1.14.2)
Requires-Dist: torch (>=1.0.0)
Requires-Dist: tqdm (>=4.19.9)
Requires-Dist: matplotlib (>=2.1.0)
Requires-Dist: gym (>=0.10.4)
Requires-Dist: scikit-image (>=0.13.1)
Requires-Dist: scikit-learn (>=0.19.1)
Requires-Dist: opencv-python (>=3.4.0.12)
Requires-Dist: pytest (>=3.4.0)
Requires-Dist: scipy (>=1.1.0)
Requires-Dist: cython (>=0.28.5)
Requires-Dist: pandas (>=0.23.4)
